ros_type_description_interfaces-2.3.0.data/data/include/type_description_interfaces/type_description_interfaces/msg/field.h
ros_type_description_interfaces-2.3.0.data/data/include/type_description_interfaces/type_description_interfaces/msg/field.hpp
ros_type_description_interfaces-2.3.0.data/data/include/type_description_interfaces/type_description_interfaces/msg/field_type.h
ros_type_description_interfaces-2.3.0.data/data/include/type_description_interfaces/type_description_interfaces/msg/field_type.hpp
ros_type_description_interfaces-2.3.0.data/data/include/type_description_interfaces/type_description_interfaces/msg/individual_type_description.h
ros_type_description_interfaces-2.3.0.data/data/include/type_description_interfaces/type_description_interfaces/msg/individual_type_description.hpp
ros_type_description_interfaces-2.3.0.data/data/include/type_description_interfaces/type_description_interfaces/msg/key_value.h
ros_type_description_interfaces-2.3.0.data/data/include/type_description_interfaces/type_description_interfaces/msg/key_value.hpp
ros_type_description_interfaces-2.3.0.data/data/include/type_description_interfaces/type_description_interfaces/msg/rosidl_generator_c__visibility_control.h
ros_type_description_interfaces-2.3.0.data/data/include/type_description_interfaces/type_description_interfaces/msg/rosidl_generator_cpp__visibility_control.hpp
ros_type_description_interfaces-2.3.0.data/data/include/type_description_interfaces/type_description_interfaces/msg/rosidl_typesupport_fastrtps_c__visibility_control.h
ros_type_description_interfaces-2.3.0.data/data/include/type_description_interfaces/type_description_interfaces/msg/rosidl_typesupport_fastrtps_cpp__visibility_control.h
ros_type_description_interfaces-2.3.0.data/data/include/type_description_interfaces/type_description_interfaces/msg/rosidl_typesupport_introspection_c__visibility_control.h
ros_type_description_interfaces-2.3.0.data/data/lib/python3.13/site-packages/type_description_interfaces-2.3.0-py3.13.egg-info/PKG-INFO
ros_type_description_interfaces-2.3.0.data/data/lib/python3.13/site-packages/type_description_interfaces-2.3.0-py3.13.egg-info/SOURCES.txt
ros_type_description_interfaces-2.3.0.data/data/lib/python3.13/site-packages/type_description_interfaces-2.3.0-py3.13.egg-info/dependency_links.txt
ros_type_description_interfaces-2.3.0.data/data/lib/python3.13/site-packages/type_description_interfaces-2.3.0-py3.13.egg-info/top_level.txt
ros_type_description_interfaces-2.3.0.dist-info/METADATA
ros_type_description_interfaces-2.3.0.dist-info/WHEEL
ros_type_description_interfaces-2.3.0.dist-info/top_level.txt
ros_type_description_interfaces-2.3.0.dist-info/RECORD
