Metadata-Version: 2.4
Name: ros-type-description-interfaces
Version: 2.3.0
Summary: A ROS package providing message and service definitions for describing and communicating descriptions of other ROS interface types.
Requires-Dist: ros-service-msgs~=2.3.0
Requires-Dist: ros-rosidl-core-runtime~=0.3.1
Dynamic: description
Dynamic: description-content-type
Dynamic: requires-dist
Dynamic: summary
